{
  "תאופיק שמס מג'דל שמס פנתר": "תאופיק שמס מג'דל שמס פנתר",
  "~ הקינג😎": "~ הקינג😎",
  "~ אלישע סבן": "~ אלישע סבן",
  "לוי מור יוסף": "לוי מור יוסף",
  "~ אליהו קליינברג": "~ אליהו קליינברג",
  "~ צחי טוויג": "~ צחי טוויג",
  "~ Mrs": "~ Mrs",
  "~ יניב ליאור": "~ יניב ליאור",
  "רונן אזרזר": "רונן אזרזר",
  "שי קרמר,מרום גולן, לנדקרוזר": "שי קרמר,מרום גולן, לנדקרוזר",
  "~ מתנאל": "~ מתנאל",
  "אלבר": "אלבר",
  "דוד מלאכי פנתר נוב פראדו": "דוד מלאכי פנתר נוב פראדו",
  "עמיקם קהתי, קצרין, פנתר - טנדר מזדה": "עמיקם קהתי, קצרין, פנתר - טנדר מזדה",
  "מתנאל מזוז פנתר אאוטלנדר": "מתנאל מזוז פנתר אאוטלנדר",
  "‪+972 54‑552‑4553‬": "‪+972 54‑552‑4553‬",
  "‪+972 50‑291‑6313‬": "‪+972 50‑291‑6313‬",
  "ינון סרוסי פנתר מטולה פראדו": "ינון סרוסי פנתר מטולה פראדו",
  "~ שחר הפנר": "~ שחר הפנר",
  "~ עופר עמיר שמאי רכוש": "~ עופר עמיר שמאי רכוש",
  "לייזי שטרן סמנכ״ל ידידים": "לייזי שטרן סמנכ״ל ידידים",
  "עמיעד פוקסמן": "עמיעד פוקסמן",
  "~ אב\"ש לוין": "~ אב\"ש לוין",
  "אבשלום ברנוי קצרין פנתר": "אבשלום ברנוי קצרין פנתר",
  "~ נועם": "~ נועם",
  "~ Rafi Shamir": "~ Rafi Shamir",
  "שילה ליבוביץ פנתר נוב דוג׳ ראם": "שילה ליבוביץ פנתר נוב דוג׳ ראם",
  "צבי השכל פנתר נטור היילקס": "צבי השכל פנתר נטור היילקס",
  "דור דביר 5015 קצרין רכז ציוד גולן": "דור דביר 5015 קצרין רכז ציוד גולן",
  "מיכל לביא כתריאל ידידים": "מיכל לביא כתריאל ידידים",
  "~ ישראל טהרני": "~ ישראל טהרני",
  "יוחאי בן צבי": "יוחאי בן צבי",
  "~ אלי": "~ אלי",
  "~ יניב אזנקוט": "~ יניב אזנקוט",
  "יהודה פלסר פנתר, אבני איתן": "יהודה פלסר פנתר, אבני איתן",
  "אבי דוילה": "אבי דוילה",
  "מאיר סלינסקי, חד נס": "מאיר סלינסקי, חד נס",
  "שמעון יפרח פנתר, צפת": "שמעון יפרח פנתר, צפת",
  "~ Mordy": "~ Mordy",
  "מוטי יאיר": "מוטי יאיר",
  "יוסף פרנקפורט פנתר, שעל, ג׳ימיני": "יוסף פרנקפורט פנתר, שעל, ג׳ימיני",
  "~ בנצי מזכיר היחידה לאיתור נעדרים": "~ בנצי מזכיר היחידה לאיתור נעדרים",
  "~ Dr. Roy Gilad Dentist": "~ Dr. Roy Gilad Dentist",
  "~ אבינועם  אסף": "~ אבינועם  אסף",
  "~ דני יוריק": "~ דני יוריק",
  "~ Stav B.H": "~ Stav B.H",
  "יהוא לוין": "יהוא לוין",
  "אליה חפוסוב לב רחום אניעם": "אליה חפוסוב לב רחום אניעם",
  "שמואל אוחנונה פאג׳רו יסוד המעלה. פנתר": "שמואל אוחנונה פאג׳רו יסוד המעלה. פנתר",
  "לאה ארלנק פנתר, קבוצת משוב": "לאה ארלנק פנתר, קבוצת משוב",
  "~ אילון": "~ אילון",
  "~ נאוה דאסה": "~ נאוה דאסה",
  "~ הלל קול": "~ הלל קול",
  "~ דביר שמידט": "~ דביר שמידט",
  "רעי לפיד פנתר, יונתן, טרייטון": "רעי לפיד פנתר, יונתן, טרייטון",
  "~ Shay Yona": "~ Shay Yona",
  "~ משה": "~ משה",
  "~ מתניה": "~ מתניה"
}